MANIFEST.in
README.rst
setup.py
django_googleplay_api.egg-info/PKG-INFO
django_googleplay_api.egg-info/SOURCES.txt
django_googleplay_api.egg-info/dependency_links.txt
django_googleplay_api.egg-info/not-zip-safe
django_googleplay_api.egg-info/requires.txt
django_googleplay_api.egg-info/top_level.txt
djgpa/__init__.py
djgpa/admin.py
djgpa/api.py
djgpa/configs.py
djgpa/models.py
djgpa/pb2.py
djgpa/test_cases.py
djgpa/test_settings.py
djgpa/urls.py
djgpa/views.py
djgpa/migrations/0001_initial.py
djgpa/migrations/__init__.py
requirements/package.txt
requirements/tests.txt